refract_serving/README.md
refract_serving/__init__.py
refract_serving/app.py
refract_serving/constants.py
refract_serving/init_script.sh
refract_serving/requirements.txt
refract_serving/utils.py
refract_serving-1.0.25.dist-info/METADATA
refract_serving-1.0.25.dist-info/WHEEL
refract_serving-1.0.25.dist-info/top_level.txt
refract_serving-1.0.25.dist-info/RECORD
