Metadata-Version: 2.1
Name: refract-serving
Version: 1.0.25
Summary: Batch prediction recipe
Home-page: UNKNOWN
Author: Amit Boke
License: UNKNOWN
Platform: UNKNOWN
Classifier: Programming Language :: Python :: 3.8
Requires-Python: >=3.8,<3.10
Requires-Dist: refractml
Requires-Dist: refractio[local]
